src/__init__.py
src/convert.py
tests/__init__.py
tests/test_convert.py
owntrack2gpx-0.1.8.dist-info/METADATA
owntrack2gpx-0.1.8.dist-info/WHEEL
owntrack2gpx-0.1.8.dist-info/entry_points.txt
owntrack2gpx-0.1.8.dist-info/top_level.txt
owntrack2gpx-0.1.8.dist-info/RECORD
