Metadata-Version: 2.1
Name: owntrack2gpx
Version: 0.1.8
Requires-Dist: gpx ==0.2.1
Requires-Dist: gpxpy ==1.5.0
